{
  "q":"wordpress",
  "remote_images":[
    {
      "id":null,
      "image_id":null,
      "name":null,
      "repository":"tutum/wordpress",
      "tag":null,
      "description":"Wordpress Docker image - listens in port 80.",
      "keywords":null,
      "recommended":false,
      "type":null,
      "links":[],
      "ports":[],
      "expose":[],
      "environment":{},
      "volumes":[],
      "created_at":null,
      "updated_at":null,
      "is_official":false,
      "is_trusted":true,
      "star_count":7
    }
  ],
  "local_images":[],
  "templates":[
    {
      "id":1,
      "name":"Wordpress",
      "description":"This is a wordpress template",
      "keywords":null,
      "recommended":true,
      "type": "wordpress",
      "created_at":"2014-04-17T16:07:35.690Z",
      "updated_at":"2014-04-17T16:07:35.690Z",
      "image_count":2
    }
  ]
}
